setup.py
student_bsu_by/__init__.py
student_bsu_by/exceptions.py
student_bsu_by/student.py
student_bsu_by.egg-info/PKG-INFO
student_bsu_by.egg-info/SOURCES.txt
student_bsu_by.egg-info/dependency_links.txt
student_bsu_by.egg-info/requires.txt
student_bsu_by.egg-info/top_level.txt