Metadata-Version: 1.0
Name: student-bsu-by
Version: 0.5.0rc1
Summary: Tool for getting various student information from student.bsu.by website.
Home-page: https://github.com/teryokhin/student_bsu_by
Author: Maxim Teryokhin, Ilya Medyanikov
Author-email: max.teryokhin@gmail.com
License: MIT
Platform: UNKNOWN
